README.rst
setup.py
google_alerts/__init__.py
google_alerts/cli/__init__.py
google_alerts/cli/manage.py
google_alerts_v2.egg-info/PKG-INFO
google_alerts_v2.egg-info/SOURCES.txt
google_alerts_v2.egg-info/dependency_links.txt
google_alerts_v2.egg-info/entry_points.txt
google_alerts_v2.egg-info/not-zip-safe
google_alerts_v2.egg-info/requires.txt
google_alerts_v2.egg-info/top_level.txt