Metadata-Version: 1.1
Name: google-alerts-v2
Version: 0.2.10
Summary: Abstraction to manage Google Alerts from code
Home-page: https://github.com/rockerbox/google-alerts
Author: Brandon Dixon
Author-email: brandon@9bplus.com
License: MIT
Download-URL: https://github.com/rockerbox/google-alerts/archive/master.zip
Keywords: google,alerts,automation,administration
Platform: UNKNOWN
Classifier: Development Status :: 4 - Beta
Classifier: Intended Audience :: Developers
Classifier: License :: OSI Approved :: MIT License
Classifier: Natural Language :: English
Classifier: Programming Language :: Python
Classifier: Topic :: Software Development :: Libraries
